odoo/addons/l10n_ro_account/README.rst
odoo/addons/l10n_ro_account/__init__.py
odoo/addons/l10n_ro_account/__manifest__.py
odoo/addons/l10n_ro_account/i18n/l10n_ro_account.pot
odoo/addons/l10n_ro_account/i18n/ro.po
odoo/addons/l10n_ro_account/models/__init__.py
odoo/addons/l10n_ro_account/models/account_account.py
odoo/addons/l10n_ro_account/models/account_payment.py
odoo/addons/l10n_ro_account/readme/CONTRIBUTORS.md
odoo/addons/l10n_ro_account/readme/DESCRIPTION.md
odoo/addons/l10n_ro_account/static/description/icon.png
odoo/addons/l10n_ro_account/static/description/index.html
odoo/addons/l10n_ro_account/tests/__init__.py
odoo/addons/l10n_ro_account/tests/test_account.py
odoo/addons/l10n_ro_account/tests/test_payment.py
odoo/addons/l10n_ro_account/wizard/__init__.py
odoo/addons/l10n_ro_account/wizard/account_payment_register.py
odoo_addon_l10n_ro_account-19.0.0.5.0.dist-info/METADATA
odoo_addon_l10n_ro_account-19.0.0.5.0.dist-info/WHEEL
odoo_addon_l10n_ro_account-19.0.0.5.0.dist-info/top_level.txt
odoo_addon_l10n_ro_account-19.0.0.5.0.dist-info/RECORD
